torchchem/__init__.py
torchchem/models/__init__.py
torchchem/models/data_utils.py
torchchem/models/neural_fp.py
torchchem/models/transformer.py
torchchem/models/utils.py
torchchem/models/tests/__init__.py
torchchem/models/tests/test_mat.py
torchchem-0.0.1.dist-info/AUTHORS
torchchem-0.0.1.dist-info/LICENSE
torchchem-0.0.1.dist-info/METADATA
torchchem-0.0.1.dist-info/WHEEL
torchchem-0.0.1.dist-info/pbr.json
torchchem-0.0.1.dist-info/top_level.txt
torchchem-0.0.1.dist-info/RECORD
