Metadata-Version: 2.1
Name: torchchem
Version: 0.0.1
Summary: PyTorch models for deep chemistry
Home-page: https://github.com/deepchem/torchchem
Author: torchchem contributors
License: UNKNOWN
Platform: UNKNOWN
Classifier: Programming Language :: Python :: 3
Classifier: License :: OSI Approved :: MIT License
Classifier: Operating System :: OS Independent
Requires-Python: >=3.6
